dummyauthenticator/__init__.py
dummyauthenticator/dummyauthenticator.py
jupyterhub_dummyauthenticator-0.3.1.dist-info/DESCRIPTION.rst
jupyterhub_dummyauthenticator-0.3.1.dist-info/METADATA
jupyterhub_dummyauthenticator-0.3.1.dist-info/RECORD
jupyterhub_dummyauthenticator-0.3.1.dist-info/WHEEL
jupyterhub_dummyauthenticator-0.3.1.dist-info/metadata.json
jupyterhub_dummyauthenticator-0.3.1.dist-info/top_level.txt
